[{"username":"a","firstname":"a","name":"aa","Email":"a@a","password":"$2y$10$N3vPLcBw2ZZLYR3GIDuCFugRRYB6hA426VCXHYBVZT6thU3Ji\/txy"},{"username":"q","firstname":"q","name":"q","Email":"q@q","password":"$2y$10$buPUlufgn\/.pMkBNBRHpLeoKtfEiJ78m24yzP4ZvKah4PZLUQ6QBi"},{"username":"Michmich","firstname":"Michel","name":"Michet","Email":"Michel.Michet@JSP.ch","password":"$2y$10$No0wZ\/yNEUFatVdu48kPDuo7CrPviPnl5\/13wyWskRS.81nPzfmym"},{"username":"LosPolos","firstname":"Paulo","name":"Lavabo","Email":"PabloLavabo@gmail.com","password":"$2y$10$Vbtwb0KaQalYJTVjGvfHSeMxbKTL35YDNXa6y\/bLKxReLqvtqPmrG"}]